setup.py
example66447.egg-info/PKG-INFO
example66447.egg-info/SOURCES.txt
example66447.egg-info/dependency_links.txt
example66447.egg-info/top_level.txt
exmpl2/__init__.py