Metadata-Version: 1.0
Name: example66447
Version: 0.0.1
Summary: example
Home-page: UNKNOWN
Author: UNKNOWN
Author-email: UNKNOWN
License: UNKNOWN
Platform: UNKNOWN
